hack4u/__init__.py
hack4u/courses.py
hack4u/utils.py
Prueba_hack4u-0.1.0.dist-info/METADATA
Prueba_hack4u-0.1.0.dist-info/WHEEL
Prueba_hack4u-0.1.0.dist-info/top_level.txt
Prueba_hack4u-0.1.0.dist-info/RECORD
